pytest_data_suites/__init__.py
pytest_data_suites/py.typed
pytest_data_suites/suite.py
pytest_data_suites/utils.py
pytest_data_suites/version.py
pytest_data_suites-1.0.5.dist-info/LICENSE
pytest_data_suites-1.0.5.dist-info/METADATA
pytest_data_suites-1.0.5.dist-info/WHEEL
pytest_data_suites-1.0.5.dist-info/RECORD
