Metadata-Version: 2.1
Name: pytest-data-suites
Version: 1.0.5
Summary: Class-based pytest parametrization
Home-page: https://github.com/reartnew/pytest-data-suites
License: MIT
Author: Artem Novikov
Author-email: artnew@list.ru
Requires-Python: >=3.8,<4.0
Classifier: Framework :: Pytest
Classifier: License :: OSI Approved :: MIT License
Classifier: Programming Language :: Python :: 3
Classifier: Programming Language :: Python :: 3.8
Classifier: Programming Language :: Python :: 3.9
Classifier: Programming Language :: Python :: 3.10
Classifier: Programming Language :: Python :: 3.11
Classifier: Programming Language :: Python :: 3.12
Classifier: Topic :: Software Development :: Testing
Classifier: Typing :: Typed
Requires-Dist: pytest (>=6.0,<9.0)
Project-URL: Repository, https://github.com/reartnew/pytest-data-suites
